cli/__init__.py
cli/check_updates.py
cli/github_client.py
cli/main.py
cli/orchestrator.py
adpcli-0.1.7.dist-info/METADATA
adpcli-0.1.7.dist-info/WHEEL
adpcli-0.1.7.dist-info/entry_points.txt
adpcli-0.1.7.dist-info/top_level.txt
adpcli-0.1.7.dist-info/RECORD
