Metadata-Version: 2.4
Name: adpcli
Version: 0.1.7
Summary: Artifact Provisioning Engine (ADP Engine) - Provisions artifacts from proyecto.yml
Requires-Python: >=3.12
Requires-Dist: pyyaml>=6.0
Requires-Dist: requests>=2.32.0
Requires-Dist: click>=8.3.0
Requires-Dist: packaging>=21.0
